{
  "id": "733-681-N--2020-05-05--13.35.49--detections",
  "model": "ResNet50_COCO_best_v2.0.1.h5",
  "summary": {
    "total": 5,
    "car": 5
  },
  "733-681-N--2020-05-05--13.35.49--detections--1--car--32.4--11x12--100.57v111.69": {
    "type": "car",
    "id": "733-681-N--2020-05-05--13.35.49--detections--1--car--32.4--11x12--100.57v111.69",
    "percentage_probability": 32.376596331596375,
    "box_points": [
      100,
      57,
      111,
      69
    ]
  },
  "733-681-N--2020-05-05--13.35.49--detections--2--car--64.4--18x21--126.72v144.93": {
    "type": "car",
    "id": "733-681-N--2020-05-05--13.35.49--detections--2--car--64.4--18x21--126.72v144.93",
    "percentage_probability": 64.41940069198608,
    "box_points": [
      126,
      72,
      144,
      93
    ]
  },
  "733-681-N--2020-05-05--13.35.49--detections--3--car--41.3--20x14--204.71v224.85": {
    "type": "car",
    "id": "733-681-N--2020-05-05--13.35.49--detections--3--car--41.3--20x14--204.71v224.85",
    "percentage_probability": 41.27697944641113,
    "box_points": [
      204,
      71,
      224,
      85
    ]
  },
  "733-681-N--2020-05-05--13.35.49--detections--4--car--44.0--26x21--199.75v225.96": {
    "type": "car",
    "id": "733-681-N--2020-05-05--13.35.49--detections--4--car--44.0--26x21--199.75v225.96",
    "percentage_probability": 44.02087330818176,
    "box_points": [
      199,
      75,
      225,
      96
    ]
  },
  "733-681-N--2020-05-05--13.35.49--detections--5--car--84.9--44x32--208.93v252.125": {
    "type": "car",
    "id": "733-681-N--2020-05-05--13.35.49--detections--5--car--84.9--44x32--208.93v252.125",
    "percentage_probability": 84.9291205406189,
    "box_points": [
      208,
      93,
      252,
      125
    ]
  }
}
