{
  "id": "733-681-N--2020-05-05--13.18.45--detections",
  "model": "ResNet50_COCO_best_v2.0.1.h5",
  "summary": {
    "total": 9,
    "car": 8,
    "bus": 1
  },
  "733-681-N--2020-05-05--13.18.45--detections--1--car--28.6--7x7--120.50v127.57": {
    "type": "car",
    "id": "733-681-N--2020-05-05--13.18.45--detections--1--car--28.6--7x7--120.50v127.57",
    "percentage_probability": 28.56595516204834,
    "box_points": [
      120,
      50,
      127,
      57
    ]
  },
  "733-681-N--2020-05-05--13.18.45--detections--2--car--45.0--9x9--107.49v116.58": {
    "type": "car",
    "id": "733-681-N--2020-05-05--13.18.45--detections--2--car--45.0--9x9--107.49v116.58",
    "percentage_probability": 44.95040476322174,
    "box_points": [
      107,
      49,
      116,
      58
    ]
  },
  "733-681-N--2020-05-05--13.18.45--detections--3--car--44.9--15x15--120.65v135.80": {
    "type": "car",
    "id": "733-681-N--2020-05-05--13.18.45--detections--3--car--44.9--15x15--120.65v135.80",
    "percentage_probability": 44.89610195159912,
    "box_points": [
      120,
      65,
      135,
      80
    ]
  },
  "733-681-N--2020-05-05--13.18.45--detections--4--car--79.9--16x17--96.68v112.85": {
    "type": "car",
    "id": "733-681-N--2020-05-05--13.18.45--detections--4--car--79.9--16x17--96.68v112.85",
    "percentage_probability": 79.89392280578613,
    "box_points": [
      96,
      68,
      112,
      85
    ]
  },
  "733-681-N--2020-05-05--13.18.45--detections--5--car--55.3--13x14--83.58v96.72": {
    "type": "car",
    "id": "733-681-N--2020-05-05--13.18.45--detections--5--car--55.3--13x14--83.58v96.72",
    "percentage_probability": 55.270981788635254,
    "box_points": [
      83,
      58,
      96,
      72
    ]
  },
  "733-681-N--2020-05-05--13.18.45--detections--6--bus--30.1--23x16--198.69v221.85": {
    "type": "bus",
    "id": "733-681-N--2020-05-05--13.18.45--detections--6--bus--30.1--23x16--198.69v221.85",
    "percentage_probability": 30.125027894973755,
    "box_points": [
      198,
      69,
      221,
      85
    ]
  },
  "733-681-N--2020-05-05--13.18.45--detections--7--car--71.0--29x27--136.85v165.112": {
    "type": "car",
    "id": "733-681-N--2020-05-05--13.18.45--detections--7--car--71.0--29x27--136.85v165.112",
    "percentage_probability": 71.02781534194946,
    "box_points": [
      136,
      85,
      165,
      112
    ]
  },
  "733-681-N--2020-05-05--13.18.45--detections--8--car--56.0--41x28--215.83v256.111": {
    "type": "car",
    "id": "733-681-N--2020-05-05--13.18.45--detections--8--car--56.0--41x28--215.83v256.111",
    "percentage_probability": 56.04854226112366,
    "box_points": [
      215,
      83,
      256,
      111
    ]
  },
  "733-681-N--2020-05-05--13.18.45--detections--9--car--89.6--37x44--103.88v140.132": {
    "type": "car",
    "id": "733-681-N--2020-05-05--13.18.45--detections--9--car--89.6--37x44--103.88v140.132",
    "percentage_probability": 89.58663940429688,
    "box_points": [
      103,
      88,
      140,
      132
    ]
  }
}
