{
  "id": "733-681-N--2020-05-05--13.17.24--detections",
  "model": "ResNet50_COCO_best_v2.0.1.h5",
  "summary": {
    "total": 4,
    "car": 4
  },
  "733-681-N--2020-05-05--13.17.24--detections--1--car--56.2--10x11--101.57v111.68": {
    "type": "car",
    "id": "733-681-N--2020-05-05--13.17.24--detections--1--car--56.2--10x11--101.57v111.68",
    "percentage_probability": 56.15382790565491,
    "box_points": [
      101,
      57,
      111,
      68
    ]
  },
  "733-681-N--2020-05-05--13.17.24--detections--2--car--26.0--30x13--133.43v163.56": {
    "type": "car",
    "id": "733-681-N--2020-05-05--13.17.24--detections--2--car--26.0--30x13--133.43v163.56",
    "percentage_probability": 26.04113221168518,
    "box_points": [
      133,
      43,
      163,
      56
    ]
  },
  "733-681-N--2020-05-05--13.17.24--detections--3--car--89.6--17x17--79.65v96.82": {
    "type": "car",
    "id": "733-681-N--2020-05-05--13.17.24--detections--3--car--89.6--17x17--79.65v96.82",
    "percentage_probability": 89.58778381347656,
    "box_points": [
      79,
      65,
      96,
      82
    ]
  },
  "733-681-N--2020-05-05--13.17.24--detections--4--car--89.8--125x79--227.159v352.238": {
    "type": "car",
    "id": "733-681-N--2020-05-05--13.17.24--detections--4--car--89.8--125x79--227.159v352.238",
    "percentage_probability": 89.76246118545532,
    "box_points": [
      227,
      159,
      352,
      238
    ]
  }
}
