{
  "id": "733-681-N--2020-05-05--13.49.19--detections",
  "model": "ResNet50_COCO_best_v2.0.1.h5",
  "summary": {
    "total": 7,
    "car": 7
  },
  "733-681-N--2020-05-05--13.49.19--detections--1--car--43.6--9x7--148.51v157.58": {
    "type": "car",
    "id": "733-681-N--2020-05-05--13.49.19--detections--1--car--43.6--9x7--148.51v157.58",
    "percentage_probability": 43.55333745479584,
    "box_points": [
      148,
      51,
      157,
      58
    ]
  },
  "733-681-N--2020-05-05--13.49.19--detections--2--car--67.2--10x10--118.52v128.62": {
    "type": "car",
    "id": "733-681-N--2020-05-05--13.49.19--detections--2--car--67.2--10x10--118.52v128.62",
    "percentage_probability": 67.24236607551575,
    "box_points": [
      118,
      52,
      128,
      62
    ]
  },
  "733-681-N--2020-05-05--13.49.19--detections--3--car--46.2--10x9--158.58v168.67": {
    "type": "car",
    "id": "733-681-N--2020-05-05--13.49.19--detections--3--car--46.2--10x9--158.58v168.67",
    "percentage_probability": 46.21281325817108,
    "box_points": [
      158,
      58,
      168,
      67
    ]
  },
  "733-681-N--2020-05-05--13.49.19--detections--4--car--60.6--11x10--143.60v154.70": {
    "type": "car",
    "id": "733-681-N--2020-05-05--13.49.19--detections--4--car--60.6--11x10--143.60v154.70",
    "percentage_probability": 60.64108610153198,
    "box_points": [
      143,
      60,
      154,
      70
    ]
  },
  "733-681-N--2020-05-05--13.49.19--detections--5--car--85.4--16x15--56.65v72.80": {
    "type": "car",
    "id": "733-681-N--2020-05-05--13.49.19--detections--5--car--85.4--16x15--56.65v72.80",
    "percentage_probability": 85.44348478317261,
    "box_points": [
      56,
      65,
      72,
      80
    ]
  },
  "733-681-N--2020-05-05--13.49.19--detections--6--car--27.1--46x32--305.115v351.147": {
    "type": "car",
    "id": "733-681-N--2020-05-05--13.49.19--detections--6--car--27.1--46x32--305.115v351.147",
    "percentage_probability": 27.10317373275757,
    "box_points": [
      305,
      115,
      351,
      147
    ]
  },
  "733-681-N--2020-05-05--13.49.19--detections--7--car--70.0--59x44--289.119v348.163": {
    "type": "car",
    "id": "733-681-N--2020-05-05--13.49.19--detections--7--car--70.0--59x44--289.119v348.163",
    "percentage_probability": 69.99260187149048,
    "box_points": [
      289,
      119,
      348,
      163
    ]
  }
}
