{
  "id": "733-681-N--2020-05-05--13.22.43--detections",
  "model": "ResNet50_COCO_best_v2.0.1.h5",
  "summary": {
    "total": 9,
    "car": 9
  },
  "733-681-N--2020-05-05--13.22.43--detections--1--car--46.9--8x8--118.51v126.59": {
    "type": "car",
    "id": "733-681-N--2020-05-05--13.22.43--detections--1--car--46.9--8x8--118.51v126.59",
    "percentage_probability": 46.904194355010986,
    "box_points": [
      118,
      51,
      126,
      59
    ]
  },
  "733-681-N--2020-05-05--13.22.43--detections--2--car--47.5--11x11--152.51v163.62": {
    "type": "car",
    "id": "733-681-N--2020-05-05--13.22.43--detections--2--car--47.5--11x11--152.51v163.62",
    "percentage_probability": 47.48920798301697,
    "box_points": [
      152,
      51,
      163,
      62
    ]
  },
  "733-681-N--2020-05-05--13.22.43--detections--3--car--28.7--9x9--157.51v166.60": {
    "type": "car",
    "id": "733-681-N--2020-05-05--13.22.43--detections--3--car--28.7--9x9--157.51v166.60",
    "percentage_probability": 28.739356994628906,
    "box_points": [
      157,
      51,
      166,
      60
    ]
  },
  "733-681-N--2020-05-05--13.22.43--detections--4--car--62.5--12x13--100.56v112.69": {
    "type": "car",
    "id": "733-681-N--2020-05-05--13.22.43--detections--4--car--62.5--12x13--100.56v112.69",
    "percentage_probability": 62.504589557647705,
    "box_points": [
      100,
      56,
      112,
      69
    ]
  },
  "733-681-N--2020-05-05--13.22.43--detections--5--car--85.7--15x15--75.71v90.86": {
    "type": "car",
    "id": "733-681-N--2020-05-05--13.22.43--detections--5--car--85.7--15x15--75.71v90.86",
    "percentage_probability": 85.68980097770691,
    "box_points": [
      75,
      71,
      90,
      86
    ]
  },
  "733-681-N--2020-05-05--13.22.43--detections--6--car--74.8--20x22--103.75v123.97": {
    "type": "car",
    "id": "733-681-N--2020-05-05--13.22.43--detections--6--car--74.8--20x22--103.75v123.97",
    "percentage_probability": 74.8496949672699,
    "box_points": [
      103,
      75,
      123,
      97
    ]
  },
  "733-681-N--2020-05-05--13.22.43--detections--7--car--63.3--30x30--24.79v54.109": {
    "type": "car",
    "id": "733-681-N--2020-05-05--13.22.43--detections--7--car--63.3--30x30--24.79v54.109",
    "percentage_probability": 63.34967017173767,
    "box_points": [
      24,
      79,
      54,
      109
    ]
  },
  "733-681-N--2020-05-05--13.22.43--detections--8--car--47.4--55x36--246.97v301.133": {
    "type": "car",
    "id": "733-681-N--2020-05-05--13.22.43--detections--8--car--47.4--55x36--246.97v301.133",
    "percentage_probability": 47.42082357406616,
    "box_points": [
      246,
      97,
      301,
      133
    ]
  },
  "733-681-N--2020-05-05--13.22.43--detections--9--car--91.8--73x69--183.122v256.191": {
    "type": "car",
    "id": "733-681-N--2020-05-05--13.22.43--detections--9--car--91.8--73x69--183.122v256.191",
    "percentage_probability": 91.84719920158386,
    "box_points": [
      183,
      122,
      256,
      191
    ]
  }
}
