{
  "id": "733-681-N--2020-05-05--13.36.34--detections",
  "model": "ResNet50_COCO_best_v2.0.1.h5",
  "summary": {
    "total": 14,
    "car": 9,
    "person": 3,
    "motorcycle": 2
  },
  "733-681-N--2020-05-05--13.36.34--detections--1--car--28.0--7x7--137.50v144.57": {
    "type": "car",
    "id": "733-681-N--2020-05-05--13.36.34--detections--1--car--28.0--7x7--137.50v144.57",
    "percentage_probability": 27.97483801841736,
    "box_points": [
      137,
      50,
      144,
      57
    ]
  },
  "733-681-N--2020-05-05--13.36.34--detections--2--car--49.7--9x9--89.56v98.65": {
    "type": "car",
    "id": "733-681-N--2020-05-05--13.36.34--detections--2--car--49.7--9x9--89.56v98.65",
    "percentage_probability": 49.74820911884308,
    "box_points": [
      89,
      56,
      98,
      65
    ]
  },
  "733-681-N--2020-05-05--13.36.34--detections--3--car--31.6--12x13--97.56v109.69": {
    "type": "car",
    "id": "733-681-N--2020-05-05--13.36.34--detections--3--car--31.6--12x13--97.56v109.69",
    "percentage_probability": 31.56370520591736,
    "box_points": [
      97,
      56,
      109,
      69
    ]
  },
  "733-681-N--2020-05-05--13.36.34--detections--4--car--61.6--11x11--100.59v111.70": {
    "type": "car",
    "id": "733-681-N--2020-05-05--13.36.34--detections--4--car--61.6--11x11--100.59v111.70",
    "percentage_probability": 61.630505323410034,
    "box_points": [
      100,
      59,
      111,
      70
    ]
  },
  "733-681-N--2020-05-05--13.36.34--detections--5--car--31.0--19x14--72.71v91.85": {
    "type": "car",
    "id": "733-681-N--2020-05-05--13.36.34--detections--5--car--31.0--19x14--72.71v91.85",
    "percentage_probability": 30.95352053642273,
    "box_points": [
      72,
      71,
      91,
      85
    ]
  },
  "733-681-N--2020-05-05--13.36.34--detections--6--person--29.2--8x11--49.79v57.90": {
    "type": "person",
    "id": "733-681-N--2020-05-05--13.36.34--detections--6--person--29.2--8x11--49.79v57.90",
    "percentage_probability": 29.19500470161438,
    "box_points": [
      49,
      79,
      57,
      90
    ]
  },
  "733-681-N--2020-05-05--13.36.34--detections--7--motorcycle--25.6--8x16--48.79v56.95": {
    "type": "motorcycle",
    "id": "733-681-N--2020-05-05--13.36.34--detections--7--motorcycle--25.6--8x16--48.79v56.95",
    "percentage_probability": 25.588977336883545,
    "box_points": [
      48,
      79,
      56,
      95
    ]
  },
  "733-681-N--2020-05-05--13.36.34--detections--8--person--33.0--9x15--49.80v58.95": {
    "type": "person",
    "id": "733-681-N--2020-05-05--13.36.34--detections--8--person--33.0--9x15--49.80v58.95",
    "percentage_probability": 32.99232721328735,
    "box_points": [
      49,
      80,
      58,
      95
    ]
  },
  "733-681-N--2020-05-05--13.36.34--detections--9--person--26.7--7x14--48.84v55.98": {
    "type": "person",
    "id": "733-681-N--2020-05-05--13.36.34--detections--9--person--26.7--7x14--48.84v55.98",
    "percentage_probability": 26.672348380088806,
    "box_points": [
      48,
      84,
      55,
      98
    ]
  },
  "733-681-N--2020-05-05--13.36.34--detections--10--motorcycle--51.0--9x13--49.86v58.99": {
    "type": "motorcycle",
    "id": "733-681-N--2020-05-05--13.36.34--detections--10--motorcycle--51.0--9x13--49.86v58.99",
    "percentage_probability": 50.98145008087158,
    "box_points": [
      49,
      86,
      58,
      99
    ]
  },
  "733-681-N--2020-05-05--13.36.34--detections--11--car--58.2--14x15--118.62v132.77": {
    "type": "car",
    "id": "733-681-N--2020-05-05--13.36.34--detections--11--car--58.2--14x15--118.62v132.77",
    "percentage_probability": 58.16184878349304,
    "box_points": [
      118,
      62,
      132,
      77
    ]
  },
  "733-681-N--2020-05-05--13.36.34--detections--12--car--79.6--22x25--71.71v93.96": {
    "type": "car",
    "id": "733-681-N--2020-05-05--13.36.34--detections--12--car--79.6--22x25--71.71v93.96",
    "percentage_probability": 79.57702279090881,
    "box_points": [
      71,
      71,
      93,
      96
    ]
  },
  "733-681-N--2020-05-05--13.36.34--detections--13--car--81.7--23x24--128.74v151.98": {
    "type": "car",
    "id": "733-681-N--2020-05-05--13.36.34--detections--13--car--81.7--23x24--128.74v151.98",
    "percentage_probability": 81.74999356269836,
    "box_points": [
      128,
      74,
      151,
      98
    ]
  },
  "733-681-N--2020-05-05--13.36.34--detections--14--car--97.2--58x33--257.104v315.137": {
    "type": "car",
    "id": "733-681-N--2020-05-05--13.36.34--detections--14--car--97.2--58x33--257.104v315.137",
    "percentage_probability": 97.1636176109314,
    "box_points": [
      257,
      104,
      315,
      137
    ]
  }
}
