{
  "id": "733-681-N--2020-05-05--13.09.22--detections",
  "model": "ResNet50_COCO_best_v2.0.1.h5",
  "summary": {
    "total": 13,
    "car": 13
  },
  "733-681-N--2020-05-05--13.09.22--detections--1--car--57.1--7x9--139.50v146.59": {
    "type": "car",
    "id": "733-681-N--2020-05-05--13.09.22--detections--1--car--57.1--7x9--139.50v146.59",
    "percentage_probability": 57.08895921707153,
    "box_points": [
      139,
      50,
      146,
      59
    ]
  },
  "733-681-N--2020-05-05--13.09.22--detections--2--car--35.3--9x8--92.53v101.61": {
    "type": "car",
    "id": "733-681-N--2020-05-05--13.09.22--detections--2--car--35.3--9x8--92.53v101.61",
    "percentage_probability": 35.33138632774353,
    "box_points": [
      92,
      53,
      101,
      61
    ]
  },
  "733-681-N--2020-05-05--13.09.22--detections--3--car--46.4--9x8--102.56v111.64": {
    "type": "car",
    "id": "733-681-N--2020-05-05--13.09.22--detections--3--car--46.4--9x8--102.56v111.64",
    "percentage_probability": 46.444499492645264,
    "box_points": [
      102,
      56,
      111,
      64
    ]
  },
  "733-681-N--2020-05-05--13.09.22--detections--4--car--50.2--9x9--117.55v126.64": {
    "type": "car",
    "id": "733-681-N--2020-05-05--13.09.22--detections--4--car--50.2--9x9--117.55v126.64",
    "percentage_probability": 50.21787881851196,
    "box_points": [
      117,
      55,
      126,
      64
    ]
  },
  "733-681-N--2020-05-05--13.09.22--detections--5--car--72.8--18x20--48.66v66.86": {
    "type": "car",
    "id": "733-681-N--2020-05-05--13.09.22--detections--5--car--72.8--18x20--48.66v66.86",
    "percentage_probability": 72.836434841156,
    "box_points": [
      48,
      66,
      66,
      86
    ]
  },
  "733-681-N--2020-05-05--13.09.22--detections--6--car--29.3--16x12--230.84v246.96": {
    "type": "car",
    "id": "733-681-N--2020-05-05--13.09.22--detections--6--car--29.3--16x12--230.84v246.96",
    "percentage_probability": 29.335930943489075,
    "box_points": [
      230,
      84,
      246,
      96
    ]
  },
  "733-681-N--2020-05-05--13.09.22--detections--7--car--26.2--8x10--238.86v246.96": {
    "type": "car",
    "id": "733-681-N--2020-05-05--13.09.22--detections--7--car--26.2--8x10--238.86v246.96",
    "percentage_probability": 26.2167751789093,
    "box_points": [
      238,
      86,
      246,
      96
    ]
  },
  "733-681-N--2020-05-05--13.09.22--detections--8--car--38.1--28x17--219.80v247.97": {
    "type": "car",
    "id": "733-681-N--2020-05-05--13.09.22--detections--8--car--38.1--28x17--219.80v247.97",
    "percentage_probability": 38.06098997592926,
    "box_points": [
      219,
      80,
      247,
      97
    ]
  },
  "733-681-N--2020-05-05--13.09.22--detections--9--car--43.2--30x27--140.88v170.115": {
    "type": "car",
    "id": "733-681-N--2020-05-05--13.09.22--detections--9--car--43.2--30x27--140.88v170.115",
    "percentage_probability": 43.223732709884644,
    "box_points": [
      140,
      88,
      170,
      115
    ]
  },
  "733-681-N--2020-05-05--13.09.22--detections--10--car--75.1--54x33--225.107v279.140": {
    "type": "car",
    "id": "733-681-N--2020-05-05--13.09.22--detections--10--car--75.1--54x33--225.107v279.140",
    "percentage_probability": 75.10040402412415,
    "box_points": [
      225,
      107,
      279,
      140
    ]
  },
  "733-681-N--2020-05-05--13.09.22--detections--11--car--72.6--97x54--153.184v250.238": {
    "type": "car",
    "id": "733-681-N--2020-05-05--13.09.22--detections--11--car--72.6--97x54--153.184v250.238",
    "percentage_probability": 72.63901233673096,
    "box_points": [
      153,
      184,
      250,
      238
    ]
  },
  "733-681-N--2020-05-05--13.09.22--detections--12--car--37.6--80x37--266.202v346.239": {
    "type": "car",
    "id": "733-681-N--2020-05-05--13.09.22--detections--12--car--37.6--80x37--266.202v346.239",
    "percentage_probability": 37.61839270591736,
    "box_points": [
      266,
      202,
      346,
      239
    ]
  },
  "733-681-N--2020-05-05--13.09.22--detections--13--car--25.2--162x68--159.170v321.238": {
    "type": "car",
    "id": "733-681-N--2020-05-05--13.09.22--detections--13--car--25.2--162x68--159.170v321.238",
    "percentage_probability": 25.233349204063416,
    "box_points": [
      159,
      170,
      321,
      238
    ]
  }
}
