{
  "id": "733-681-N--2020-05-05--13.15.31--detections",
  "model": "ResNet50_COCO_best_v2.0.1.h5",
  "summary": {
    "total": 9,
    "car": 8,
    "bus": 1
  },
  "733-681-N--2020-05-05--13.15.31--detections--1--car--37.7--8x8--98.50v106.58": {
    "type": "car",
    "id": "733-681-N--2020-05-05--13.15.31--detections--1--car--37.7--8x8--98.50v106.58",
    "percentage_probability": 37.71458864212036,
    "box_points": [
      98,
      50,
      106,
      58
    ]
  },
  "733-681-N--2020-05-05--13.15.31--detections--2--car--69.2--14x13--173.66v187.79": {
    "type": "car",
    "id": "733-681-N--2020-05-05--13.15.31--detections--2--car--69.2--14x13--173.66v187.79",
    "percentage_probability": 69.19184923171997,
    "box_points": [
      173,
      66,
      187,
      79
    ]
  },
  "733-681-N--2020-05-05--13.15.31--detections--3--car--79.2--15x15--101.68v116.83": {
    "type": "car",
    "id": "733-681-N--2020-05-05--13.15.31--detections--3--car--79.2--15x15--101.68v116.83",
    "percentage_probability": 79.15308475494385,
    "box_points": [
      101,
      68,
      116,
      83
    ]
  },
  "733-681-N--2020-05-05--13.15.31--detections--4--car--25.8--7x11--170.68v177.79": {
    "type": "car",
    "id": "733-681-N--2020-05-05--13.15.31--detections--4--car--25.8--7x11--170.68v177.79",
    "percentage_probability": 25.772899389266968,
    "box_points": [
      170,
      68,
      177,
      79
    ]
  },
  "733-681-N--2020-05-05--13.15.31--detections--5--car--44.8--18x16--158.70v176.86": {
    "type": "car",
    "id": "733-681-N--2020-05-05--13.15.31--detections--5--car--44.8--18x16--158.70v176.86",
    "percentage_probability": 44.81469988822937,
    "box_points": [
      158,
      70,
      176,
      86
    ]
  },
  "733-681-N--2020-05-05--13.15.31--detections--6--bus--77.0--51x87--59.97v110.184": {
    "type": "bus",
    "id": "733-681-N--2020-05-05--13.15.31--detections--6--bus--77.0--51x87--59.97v110.184",
    "percentage_probability": 76.97662115097046,
    "box_points": [
      59,
      97,
      110,
      184
    ]
  },
  "733-681-N--2020-05-05--13.15.31--detections--7--car--96.6--53x48--154.119v207.167": {
    "type": "car",
    "id": "733-681-N--2020-05-05--13.15.31--detections--7--car--96.6--53x48--154.119v207.167",
    "percentage_probability": 96.62615060806274,
    "box_points": [
      154,
      119,
      207,
      167
    ]
  },
  "733-681-N--2020-05-05--13.15.31--detections--8--car--80.1--77x52--267.130v344.182": {
    "type": "car",
    "id": "733-681-N--2020-05-05--13.15.31--detections--8--car--80.1--77x52--267.130v344.182",
    "percentage_probability": 80.1293671131134,
    "box_points": [
      267,
      130,
      344,
      182
    ]
  },
  "733-681-N--2020-05-05--13.15.31--detections--9--car--66.5--53x88--59.102v112.190": {
    "type": "car",
    "id": "733-681-N--2020-05-05--13.15.31--detections--9--car--66.5--53x88--59.102v112.190",
    "percentage_probability": 66.52213335037231,
    "box_points": [
      59,
      102,
      112,
      190
    ]
  }
}
