{
  "id": "733-681-N--2020-05-05--13.49.07--detections",
  "model": "ResNet50_COCO_best_v2.0.1.h5",
  "summary": {
    "total": 3,
    "car": 3
  },
  "733-681-N--2020-05-05--13.49.07--detections--1--car--59.7--14x14--118.61v132.75": {
    "type": "car",
    "id": "733-681-N--2020-05-05--13.49.07--detections--1--car--59.7--14x14--118.61v132.75",
    "percentage_probability": 59.71684455871582,
    "box_points": [
      118,
      61,
      132,
      75
    ]
  },
  "733-681-N--2020-05-05--13.49.07--detections--2--car--64.0--35x39--107.95v142.134": {
    "type": "car",
    "id": "733-681-N--2020-05-05--13.49.07--detections--2--car--64.0--35x39--107.95v142.134",
    "percentage_probability": 63.99710178375244,
    "box_points": [
      107,
      95,
      142,
      134
    ]
  },
  "733-681-N--2020-05-05--13.49.07--detections--3--car--88.5--40x41--141.83v181.124": {
    "type": "car",
    "id": "733-681-N--2020-05-05--13.49.07--detections--3--car--88.5--40x41--141.83v181.124",
    "percentage_probability": 88.45939636230469,
    "box_points": [
      141,
      83,
      181,
      124
    ]
  }
}
