{
  "id": "733-681-N--2020-05-05--13.53.07--detections",
  "model": "ResNet50_COCO_best_v2.0.1.h5",
  "summary": {
    "total": 4,
    "car": 3,
    "bus": 1
  },
  "733-681-N--2020-05-05--13.53.07--detections--1--car--63.9--15x17--101.63v116.80": {
    "type": "car",
    "id": "733-681-N--2020-05-05--13.53.07--detections--1--car--63.9--15x17--101.63v116.80",
    "percentage_probability": 63.93423676490784,
    "box_points": [
      101,
      63,
      116,
      80
    ]
  },
  "733-681-N--2020-05-05--13.53.07--detections--2--bus--59.9--15x17--101.63v116.80": {
    "type": "bus",
    "id": "733-681-N--2020-05-05--13.53.07--detections--2--bus--59.9--15x17--101.63v116.80",
    "percentage_probability": 59.896934032440186,
    "box_points": [
      101,
      63,
      116,
      80
    ]
  },
  "733-681-N--2020-05-05--13.53.07--detections--3--car--75.9--25x26--107.85v132.111": {
    "type": "car",
    "id": "733-681-N--2020-05-05--13.53.07--detections--3--car--75.9--25x26--107.85v132.111",
    "percentage_probability": 75.94118118286133,
    "box_points": [
      107,
      85,
      132,
      111
    ]
  },
  "733-681-N--2020-05-05--13.53.07--detections--4--car--97.4--53x47--159.109v212.156": {
    "type": "car",
    "id": "733-681-N--2020-05-05--13.53.07--detections--4--car--97.4--53x47--159.109v212.156",
    "percentage_probability": 97.3684310913086,
    "box_points": [
      159,
      109,
      212,
      156
    ]
  }
}
