{
  "id": "733-681-N--2020-05-05--13.47.44--detections",
  "model": "ResNet50_COCO_best_v2.0.1.h5",
  "summary": {
    "total": 5,
    "car": 5
  },
  "733-681-N--2020-05-05--13.47.44--detections--1--car--37.4--8x7--146.49v154.56": {
    "type": "car",
    "id": "733-681-N--2020-05-05--13.47.44--detections--1--car--37.4--8x7--146.49v154.56",
    "percentage_probability": 37.35548257827759,
    "box_points": [
      146,
      49,
      154,
      56
    ]
  },
  "733-681-N--2020-05-05--13.47.44--detections--2--car--38.5--9x9--159.60v168.69": {
    "type": "car",
    "id": "733-681-N--2020-05-05--13.47.44--detections--2--car--38.5--9x9--159.60v168.69",
    "percentage_probability": 38.501083850860596,
    "box_points": [
      159,
      60,
      168,
      69
    ]
  },
  "733-681-N--2020-05-05--13.47.44--detections--3--car--54.9--20x16--174.66v194.82": {
    "type": "car",
    "id": "733-681-N--2020-05-05--13.47.44--detections--3--car--54.9--20x16--174.66v194.82",
    "percentage_probability": 54.8761248588562,
    "box_points": [
      174,
      66,
      194,
      82
    ]
  },
  "733-681-N--2020-05-05--13.47.44--detections--4--car--58.4--31x30--28.80v59.110": {
    "type": "car",
    "id": "733-681-N--2020-05-05--13.47.44--detections--4--car--58.4--31x30--28.80v59.110",
    "percentage_probability": 58.42215418815613,
    "box_points": [
      28,
      80,
      59,
      110
    ]
  },
  "733-681-N--2020-05-05--13.47.44--detections--5--car--92.8--67x41--280.110v347.151": {
    "type": "car",
    "id": "733-681-N--2020-05-05--13.47.44--detections--5--car--92.8--67x41--280.110v347.151",
    "percentage_probability": 92.77727007865906,
    "box_points": [
      280,
      110,
      347,
      151
    ]
  }
}
