{
  "id": "733-681-N--2020-05-05--13.51.23--detections",
  "model": "ResNet50_COCO_best_v2.0.1.h5",
  "summary": {
    "total": 5,
    "car": 4,
    "bus": 1
  },
  "733-681-N--2020-05-05--13.51.23--detections--1--car--52.2--10x11--118.57v128.68": {
    "type": "car",
    "id": "733-681-N--2020-05-05--13.51.23--detections--1--car--52.2--10x11--118.57v128.68",
    "percentage_probability": 52.22032070159912,
    "box_points": [
      118,
      57,
      128,
      68
    ]
  },
  "733-681-N--2020-05-05--13.51.23--detections--2--car--51.4--17x20--75.64v92.84": {
    "type": "car",
    "id": "733-681-N--2020-05-05--13.51.23--detections--2--car--51.4--17x20--75.64v92.84",
    "percentage_probability": 51.38162970542908,
    "box_points": [
      75,
      64,
      92,
      84
    ]
  },
  "733-681-N--2020-05-05--13.51.23--detections--3--bus--25.4--17x20--75.64v92.84": {
    "type": "bus",
    "id": "733-681-N--2020-05-05--13.51.23--detections--3--bus--25.4--17x20--75.64v92.84",
    "percentage_probability": 25.403785705566406,
    "box_points": [
      75,
      64,
      92,
      84
    ]
  },
  "733-681-N--2020-05-05--13.51.23--detections--4--car--69.5--27x21--194.75v221.96": {
    "type": "car",
    "id": "733-681-N--2020-05-05--13.51.23--detections--4--car--69.5--27x21--194.75v221.96",
    "percentage_probability": 69.51237916946411,
    "box_points": [
      194,
      75,
      221,
      96
    ]
  },
  "733-681-N--2020-05-05--13.51.23--detections--5--car--79.3--24x23--130.81v154.104": {
    "type": "car",
    "id": "733-681-N--2020-05-05--13.51.23--detections--5--car--79.3--24x23--130.81v154.104",
    "percentage_probability": 79.2933702468872,
    "box_points": [
      130,
      81,
      154,
      104
    ]
  }
}
