{
  "id": "733-681-N--2020-05-05--13.55.59--detections",
  "model": "ResNet50_COCO_best_v2.0.1.h5",
  "summary": {
    "total": 5,
    "car": 4,
    "bus": 1
  },
  "733-681-N--2020-05-05--13.55.59--detections--1--car--50.7--11x12--101.56v112.68": {
    "type": "car",
    "id": "733-681-N--2020-05-05--13.55.59--detections--1--car--50.7--11x12--101.56v112.68",
    "percentage_probability": 50.71367025375366,
    "box_points": [
      101,
      56,
      112,
      68
    ]
  },
  "733-681-N--2020-05-05--13.55.59--detections--2--car--32.3--14x13--178.61v192.74": {
    "type": "car",
    "id": "733-681-N--2020-05-05--13.55.59--detections--2--car--32.3--14x13--178.61v192.74",
    "percentage_probability": 32.336002588272095,
    "box_points": [
      178,
      61,
      192,
      74
    ]
  },
  "733-681-N--2020-05-05--13.55.59--detections--3--car--25.7--21x17--101.77v122.94": {
    "type": "car",
    "id": "733-681-N--2020-05-05--13.55.59--detections--3--car--25.7--21x17--101.77v122.94",
    "percentage_probability": 25.743484497070312,
    "box_points": [
      101,
      77,
      122,
      94
    ]
  },
  "733-681-N--2020-05-05--13.55.59--detections--4--car--75.6--23x25--101.79v124.104": {
    "type": "car",
    "id": "733-681-N--2020-05-05--13.55.59--detections--4--car--75.6--23x25--101.79v124.104",
    "percentage_probability": 75.6433367729187,
    "box_points": [
      101,
      79,
      124,
      104
    ]
  },
  "733-681-N--2020-05-05--13.55.59--detections--5--bus--93.3--49x37--222.82v271.119": {
    "type": "bus",
    "id": "733-681-N--2020-05-05--13.55.59--detections--5--bus--93.3--49x37--222.82v271.119",
    "percentage_probability": 93.32841038703918,
    "box_points": [
      222,
      82,
      271,
      119
    ]
  }
}
