{
  "id": "733-681-N--2020-05-05--13.44.11--detections",
  "model": "ResNet50_COCO_best_v2.0.1.h5",
  "summary": {
    "total": 10,
    "car": 9,
    "bus": 1
  },
  "733-681-N--2020-05-05--13.44.11--detections--1--car--49.2--9x9--118.53v127.62": {
    "type": "car",
    "id": "733-681-N--2020-05-05--13.44.11--detections--1--car--49.2--9x9--118.53v127.62",
    "percentage_probability": 49.22301471233368,
    "box_points": [
      118,
      53,
      127,
      62
    ]
  },
  "733-681-N--2020-05-05--13.44.11--detections--2--car--33.6--11x11--155.55v166.66": {
    "type": "car",
    "id": "733-681-N--2020-05-05--13.44.11--detections--2--car--33.6--11x11--155.55v166.66",
    "percentage_probability": 33.56650471687317,
    "box_points": [
      155,
      55,
      166,
      66
    ]
  },
  "733-681-N--2020-05-05--13.44.11--detections--3--car--38.3--10x11--89.57v99.68": {
    "type": "car",
    "id": "733-681-N--2020-05-05--13.44.11--detections--3--car--38.3--10x11--89.57v99.68",
    "percentage_probability": 38.25600743293762,
    "box_points": [
      89,
      57,
      99,
      68
    ]
  },
  "733-681-N--2020-05-05--13.44.11--detections--4--car--64.2--13x14--80.64v93.78": {
    "type": "car",
    "id": "733-681-N--2020-05-05--13.44.11--detections--4--car--64.2--13x14--80.64v93.78",
    "percentage_probability": 64.22297954559326,
    "box_points": [
      80,
      64,
      93,
      78
    ]
  },
  "733-681-N--2020-05-05--13.44.11--detections--5--car--85.5--16x17--99.67v115.84": {
    "type": "car",
    "id": "733-681-N--2020-05-05--13.44.11--detections--5--car--85.5--16x17--99.67v115.84",
    "percentage_probability": 85.54359674453735,
    "box_points": [
      99,
      67,
      115,
      84
    ]
  },
  "733-681-N--2020-05-05--13.44.11--detections--6--car--50.7--25x20--175.64v200.84": {
    "type": "car",
    "id": "733-681-N--2020-05-05--13.44.11--detections--6--car--50.7--25x20--175.64v200.84",
    "percentage_probability": 50.74484944343567,
    "box_points": [
      175,
      64,
      200,
      84
    ]
  },
  "733-681-N--2020-05-05--13.44.11--detections--7--car--51.6--40x54--144.72v184.126": {
    "type": "car",
    "id": "733-681-N--2020-05-05--13.44.11--detections--7--car--51.6--40x54--144.72v184.126",
    "percentage_probability": 51.578789949417114,
    "box_points": [
      144,
      72,
      184,
      126
    ]
  },
  "733-681-N--2020-05-05--13.44.11--detections--8--bus--47.4--58x90--51.113v109.203": {
    "type": "bus",
    "id": "733-681-N--2020-05-05--13.44.11--detections--8--bus--47.4--58x90--51.113v109.203",
    "percentage_probability": 47.39646315574646,
    "box_points": [
      51,
      113,
      109,
      203
    ]
  },
  "733-681-N--2020-05-05--13.44.11--detections--9--car--70.4--53x47--294.145v347.192": {
    "type": "car",
    "id": "733-681-N--2020-05-05--13.44.11--detections--9--car--70.4--53x47--294.145v347.192",
    "percentage_probability": 70.4455554485321,
    "box_points": [
      294,
      145,
      347,
      192
    ]
  },
  "733-681-N--2020-05-05--13.44.11--detections--10--car--85.7--56x78--52.123v108.201": {
    "type": "car",
    "id": "733-681-N--2020-05-05--13.44.11--detections--10--car--85.7--56x78--52.123v108.201",
    "percentage_probability": 85.68962812423706,
    "box_points": [
      52,
      123,
      108,
      201
    ]
  }
}
