{
  "id": "733-681-N--2020-05-05--13.58.51--detections",
  "model": "ResNet50_COCO_best_v2.0.1.h5",
  "summary": {
    "total": 7,
    "car": 7
  },
  "733-681-N--2020-05-05--13.58.51--detections--1--car--44.6--8x7--95.52v103.59": {
    "type": "car",
    "id": "733-681-N--2020-05-05--13.58.51--detections--1--car--44.6--8x7--95.52v103.59",
    "percentage_probability": 44.648027420043945,
    "box_points": [
      95,
      52,
      103,
      59
    ]
  },
  "733-681-N--2020-05-05--13.58.51--detections--2--car--35.7--11x12--116.57v127.69": {
    "type": "car",
    "id": "733-681-N--2020-05-05--13.58.51--detections--2--car--35.7--11x12--116.57v127.69",
    "percentage_probability": 35.67281365394592,
    "box_points": [
      116,
      57,
      127,
      69
    ]
  },
  "733-681-N--2020-05-05--13.58.51--detections--3--car--60.7--10x8--142.57v152.65": {
    "type": "car",
    "id": "733-681-N--2020-05-05--13.58.51--detections--3--car--60.7--10x8--142.57v152.65",
    "percentage_probability": 60.67696809768677,
    "box_points": [
      142,
      57,
      152,
      65
    ]
  },
  "733-681-N--2020-05-05--13.58.51--detections--4--car--43.5--10x10--100.59v110.69": {
    "type": "car",
    "id": "733-681-N--2020-05-05--13.58.51--detections--4--car--43.5--10x10--100.59v110.69",
    "percentage_probability": 43.54221820831299,
    "box_points": [
      100,
      59,
      110,
      69
    ]
  },
  "733-681-N--2020-05-05--13.58.51--detections--5--car--85.7--17x18--76.69v93.87": {
    "type": "car",
    "id": "733-681-N--2020-05-05--13.58.51--detections--5--car--85.7--17x18--76.69v93.87",
    "percentage_probability": 85.68305969238281,
    "box_points": [
      76,
      69,
      93,
      87
    ]
  },
  "733-681-N--2020-05-05--13.58.51--detections--6--car--45.6--85x60--265.178v350.238": {
    "type": "car",
    "id": "733-681-N--2020-05-05--13.58.51--detections--6--car--45.6--85x60--265.178v350.238",
    "percentage_probability": 45.55557072162628,
    "box_points": [
      265,
      178,
      350,
      238
    ]
  },
  "733-681-N--2020-05-05--13.58.51--detections--7--car--77.9--64x86--55.154v119.240": {
    "type": "car",
    "id": "733-681-N--2020-05-05--13.58.51--detections--7--car--77.9--64x86--55.154v119.240",
    "percentage_probability": 77.8689980506897,
    "box_points": [
      55,
      154,
      119,
      240
    ]
  }
}
