{
  "id": "733-681-N--2020-05-05--13.17.30--detections",
  "model": "ResNet50_COCO_best_v2.0.1.h5",
  "summary": {
    "total": 6,
    "car": 6
  },
  "733-681-N--2020-05-05--13.17.30--detections--1--car--26.4--7x7--138.49v145.56": {
    "type": "car",
    "id": "733-681-N--2020-05-05--13.17.30--detections--1--car--26.4--7x7--138.49v145.56",
    "percentage_probability": 26.417341828346252,
    "box_points": [
      138,
      49,
      145,
      56
    ]
  },
  "733-681-N--2020-05-05--13.17.30--detections--2--car--40.8--8x7--107.52v115.59": {
    "type": "car",
    "id": "733-681-N--2020-05-05--13.17.30--detections--2--car--40.8--8x7--107.52v115.59",
    "percentage_probability": 40.844178199768066,
    "box_points": [
      107,
      52,
      115,
      59
    ]
  },
  "733-681-N--2020-05-05--13.17.30--detections--3--car--44.6--9x12--118.56v127.68": {
    "type": "car",
    "id": "733-681-N--2020-05-05--13.17.30--detections--3--car--44.6--9x12--118.56v127.68",
    "percentage_probability": 44.58948075771332,
    "box_points": [
      118,
      56,
      127,
      68
    ]
  },
  "733-681-N--2020-05-05--13.17.30--detections--4--car--52.6--24x18--186.74v210.92": {
    "type": "car",
    "id": "733-681-N--2020-05-05--13.17.30--detections--4--car--52.6--24x18--186.74v210.92",
    "percentage_probability": 52.58048176765442,
    "box_points": [
      186,
      74,
      210,
      92
    ]
  },
  "733-681-N--2020-05-05--13.17.30--detections--5--car--74.5--15x17--97.62v112.79": {
    "type": "car",
    "id": "733-681-N--2020-05-05--13.17.30--detections--5--car--74.5--15x17--97.62v112.79",
    "percentage_probability": 74.50474500656128,
    "box_points": [
      97,
      62,
      112,
      79
    ]
  },
  "733-681-N--2020-05-05--13.17.30--detections--6--car--97.5--102x83--150.155v252.238": {
    "type": "car",
    "id": "733-681-N--2020-05-05--13.17.30--detections--6--car--97.5--102x83--150.155v252.238",
    "percentage_probability": 97.52378463745117,
    "box_points": [
      150,
      155,
      252,
      238
    ]
  }
}
