{
  "id": "733-681-N--2020-05-05--13.33.15--detections",
  "model": "ResNet50_COCO_best_v2.0.1.h5",
  "summary": {
    "total": 15,
    "car": 13,
    "person": 1,
    "bus": 1
  },
  "733-681-N--2020-05-05--13.33.15--detections--1--car--37.2--8x11--117.48v125.59": {
    "type": "car",
    "id": "733-681-N--2020-05-05--13.33.15--detections--1--car--37.2--8x11--117.48v125.59",
    "percentage_probability": 37.22025454044342,
    "box_points": [
      117,
      48,
      125,
      59
    ]
  },
  "733-681-N--2020-05-05--13.33.15--detections--2--car--30.2--8x8--137.47v145.55": {
    "type": "car",
    "id": "733-681-N--2020-05-05--13.33.15--detections--2--car--30.2--8x8--137.47v145.55",
    "percentage_probability": 30.18033504486084,
    "box_points": [
      137,
      47,
      145,
      55
    ]
  },
  "733-681-N--2020-05-05--13.33.15--detections--3--car--26.2--9x9--165.54v174.63": {
    "type": "car",
    "id": "733-681-N--2020-05-05--13.33.15--detections--3--car--26.2--9x9--165.54v174.63",
    "percentage_probability": 26.189762353897095,
    "box_points": [
      165,
      54,
      174,
      63
    ]
  },
  "733-681-N--2020-05-05--13.33.15--detections--4--car--45.0--12x11--154.55v166.66": {
    "type": "car",
    "id": "733-681-N--2020-05-05--13.33.15--detections--4--car--45.0--12x11--154.55v166.66",
    "percentage_probability": 44.97275650501251,
    "box_points": [
      154,
      55,
      166,
      66
    ]
  },
  "733-681-N--2020-05-05--13.33.15--detections--5--car--31.1--10x12--87.58v97.70": {
    "type": "car",
    "id": "733-681-N--2020-05-05--13.33.15--detections--5--car--31.1--10x12--87.58v97.70",
    "percentage_probability": 31.096172332763672,
    "box_points": [
      87,
      58,
      97,
      70
    ]
  },
  "733-681-N--2020-05-05--13.33.15--detections--6--car--84.1--14x12--145.61v159.73": {
    "type": "car",
    "id": "733-681-N--2020-05-05--13.33.15--detections--6--car--84.1--14x12--145.61v159.73",
    "percentage_probability": 84.13441181182861,
    "box_points": [
      145,
      61,
      159,
      73
    ]
  },
  "733-681-N--2020-05-05--13.33.15--detections--7--person--54.8--11x12--322.95v333.107": {
    "type": "person",
    "id": "733-681-N--2020-05-05--13.33.15--detections--7--person--54.8--11x12--322.95v333.107",
    "percentage_probability": 54.80099320411682,
    "box_points": [
      322,
      95,
      333,
      107
    ]
  },
  "733-681-N--2020-05-05--13.33.15--detections--8--car--38.7--23x17--60.96v83.113": {
    "type": "car",
    "id": "733-681-N--2020-05-05--13.33.15--detections--8--car--38.7--23x17--60.96v83.113",
    "percentage_probability": 38.72385025024414,
    "box_points": [
      60,
      96,
      83,
      113
    ]
  },
  "733-681-N--2020-05-05--13.33.15--detections--9--car--76.9--22x21--47.70v69.91": {
    "type": "car",
    "id": "733-681-N--2020-05-05--13.33.15--detections--9--car--76.9--22x21--47.70v69.91",
    "percentage_probability": 76.88397765159607,
    "box_points": [
      47,
      70,
      69,
      91
    ]
  },
  "733-681-N--2020-05-05--13.33.15--detections--10--car--44.9--23x17--60.85v83.102": {
    "type": "car",
    "id": "733-681-N--2020-05-05--13.33.15--detections--10--car--44.9--23x17--60.85v83.102",
    "percentage_probability": 44.86454129219055,
    "box_points": [
      60,
      85,
      83,
      102
    ]
  },
  "733-681-N--2020-05-05--13.33.15--detections--11--car--85.0--35x43--104.86v139.129": {
    "type": "car",
    "id": "733-681-N--2020-05-05--13.33.15--detections--11--car--85.0--35x43--104.86v139.129",
    "percentage_probability": 85.0041151046753,
    "box_points": [
      104,
      86,
      139,
      129
    ]
  },
  "733-681-N--2020-05-05--13.33.15--detections--12--car--96.4--49x30--239.97v288.127": {
    "type": "car",
    "id": "733-681-N--2020-05-05--13.33.15--detections--12--car--96.4--49x30--239.97v288.127",
    "percentage_probability": 96.41162157058716,
    "box_points": [
      239,
      97,
      288,
      127
    ]
  },
  "733-681-N--2020-05-05--13.33.15--detections--13--car--94.9--40x42--153.92v193.134": {
    "type": "car",
    "id": "733-681-N--2020-05-05--13.33.15--detections--13--car--94.9--40x42--153.92v193.134",
    "percentage_probability": 94.90965604782104,
    "box_points": [
      153,
      92,
      193,
      134
    ]
  },
  "733-681-N--2020-05-05--13.33.15--detections--14--bus--48.1--62x97--57.140v119.237": {
    "type": "bus",
    "id": "733-681-N--2020-05-05--13.33.15--detections--14--bus--48.1--62x97--57.140v119.237",
    "percentage_probability": 48.11831712722778,
    "box_points": [
      57,
      140,
      119,
      237
    ]
  },
  "733-681-N--2020-05-05--13.33.15--detections--15--car--94.0--62x95--57.142v119.237": {
    "type": "car",
    "id": "733-681-N--2020-05-05--13.33.15--detections--15--car--94.0--62x95--57.142v119.237",
    "percentage_probability": 94.02888417243958,
    "box_points": [
      57,
      142,
      119,
      237
    ]
  }
}
