{
  "id": "733-681-N--2020-05-05--13.21.49--detections",
  "model": "ResNet50_COCO_best_v2.0.1.h5",
  "summary": {
    "total": 3,
    "car": 3
  },
  "733-681-N--2020-05-05--13.21.49--detections--1--car--33.4--13x13--97.61v110.74": {
    "type": "car",
    "id": "733-681-N--2020-05-05--13.21.49--detections--1--car--33.4--13x13--97.61v110.74",
    "percentage_probability": 33.398839831352234,
    "box_points": [
      97,
      61,
      110,
      74
    ]
  },
  "733-681-N--2020-05-05--13.21.49--detections--2--car--88.0--25x31--68.80v93.111": {
    "type": "car",
    "id": "733-681-N--2020-05-05--13.21.49--detections--2--car--88.0--25x31--68.80v93.111",
    "percentage_probability": 88.04124593734741,
    "box_points": [
      68,
      80,
      93,
      111
    ]
  },
  "733-681-N--2020-05-05--13.21.49--detections--3--car--89.4--42x26--227.90v269.116": {
    "type": "car",
    "id": "733-681-N--2020-05-05--13.21.49--detections--3--car--89.4--42x26--227.90v269.116",
    "percentage_probability": 89.41023349761963,
    "box_points": [
      227,
      90,
      269,
      116
    ]
  }
}
