{
  "id": "733-681-N--2020-05-05--13.31.31--detections",
  "model": "ResNet50_COCO_best_v2.0.1.h5",
  "summary": {
    "total": 8,
    "car": 7,
    "bus": 1
  },
  "733-681-N--2020-05-05--13.31.31--detections--1--car--51.0--7x8--119.50v126.58": {
    "type": "car",
    "id": "733-681-N--2020-05-05--13.31.31--detections--1--car--51.0--7x8--119.50v126.58",
    "percentage_probability": 51.00158452987671,
    "box_points": [
      119,
      50,
      126,
      58
    ]
  },
  "733-681-N--2020-05-05--13.31.31--detections--2--car--52.0--16x12--146.46v162.58": {
    "type": "car",
    "id": "733-681-N--2020-05-05--13.31.31--detections--2--car--52.0--16x12--146.46v162.58",
    "percentage_probability": 51.971834897994995,
    "box_points": [
      146,
      46,
      162,
      58
    ]
  },
  "733-681-N--2020-05-05--13.31.31--detections--3--car--69.9--9x9--104.52v113.61": {
    "type": "car",
    "id": "733-681-N--2020-05-05--13.31.31--detections--3--car--69.9--9x9--104.52v113.61",
    "percentage_probability": 69.85353827476501,
    "box_points": [
      104,
      52,
      113,
      61
    ]
  },
  "733-681-N--2020-05-05--13.31.31--detections--4--car--60.5--14x12--163.61v177.73": {
    "type": "car",
    "id": "733-681-N--2020-05-05--13.31.31--detections--4--car--60.5--14x12--163.61v177.73",
    "percentage_probability": 60.45934557914734,
    "box_points": [
      163,
      61,
      177,
      73
    ]
  },
  "733-681-N--2020-05-05--13.31.31--detections--5--car--69.0--19x20--75.55v94.75": {
    "type": "car",
    "id": "733-681-N--2020-05-05--13.31.31--detections--5--car--69.0--19x20--75.55v94.75",
    "percentage_probability": 68.98388862609863,
    "box_points": [
      75,
      55,
      94,
      75
    ]
  },
  "733-681-N--2020-05-05--13.31.31--detections--6--bus--35.0--19x21--75.55v94.76": {
    "type": "bus",
    "id": "733-681-N--2020-05-05--13.31.31--detections--6--bus--35.0--19x21--75.55v94.76",
    "percentage_probability": 34.978947043418884,
    "box_points": [
      75,
      55,
      94,
      76
    ]
  },
  "733-681-N--2020-05-05--13.31.31--detections--7--car--63.9--15x15--104.66v119.81": {
    "type": "car",
    "id": "733-681-N--2020-05-05--13.31.31--detections--7--car--63.9--15x15--104.66v119.81",
    "percentage_probability": 63.86756896972656,
    "box_points": [
      104,
      66,
      119,
      81
    ]
  },
  "733-681-N--2020-05-05--13.31.31--detections--8--car--65.9--29x31--320.127v349.158": {
    "type": "car",
    "id": "733-681-N--2020-05-05--13.31.31--detections--8--car--65.9--29x31--320.127v349.158",
    "percentage_probability": 65.85228443145752,
    "box_points": [
      320,
      127,
      349,
      158
    ]
  }
}
