{
  "id": "733-681-N--2020-05-05--13.59.59--detections",
  "model": "ResNet50_COCO_best_v2.0.1.h5",
  "summary": {
    "total": 7,
    "car": 6,
    "bus": 1
  },
  "733-681-N--2020-05-05--13.59.59--detections--1--car--47.5--7x8--159.52v166.60": {
    "type": "car",
    "id": "733-681-N--2020-05-05--13.59.59--detections--1--car--47.5--7x8--159.52v166.60",
    "percentage_probability": 47.54570722579956,
    "box_points": [
      159,
      52,
      166,
      60
    ]
  },
  "733-681-N--2020-05-05--13.59.59--detections--2--car--27.7--9x10--117.51v126.61": {
    "type": "car",
    "id": "733-681-N--2020-05-05--13.59.59--detections--2--car--27.7--9x10--117.51v126.61",
    "percentage_probability": 27.654650807380676,
    "box_points": [
      117,
      51,
      126,
      61
    ]
  },
  "733-681-N--2020-05-05--13.59.59--detections--3--car--38.9--12x11--102.59v114.70": {
    "type": "car",
    "id": "733-681-N--2020-05-05--13.59.59--detections--3--car--38.9--12x11--102.59v114.70",
    "percentage_probability": 38.912200927734375,
    "box_points": [
      102,
      59,
      114,
      70
    ]
  },
  "733-681-N--2020-05-05--13.59.59--detections--4--car--73.5--29x31--97.88v126.119": {
    "type": "car",
    "id": "733-681-N--2020-05-05--13.59.59--detections--4--car--73.5--29x31--97.88v126.119",
    "percentage_probability": 73.50791692733765,
    "box_points": [
      97,
      88,
      126,
      119
    ]
  },
  "733-681-N--2020-05-05--13.59.59--detections--5--bus--43.9--30x40--96.77v126.117": {
    "type": "bus",
    "id": "733-681-N--2020-05-05--13.59.59--detections--5--bus--43.9--30x40--96.77v126.117",
    "percentage_probability": 43.874767422676086,
    "box_points": [
      96,
      77,
      126,
      117
    ]
  },
  "733-681-N--2020-05-05--13.59.59--detections--6--car--38.8--101x35--169.203v270.238": {
    "type": "car",
    "id": "733-681-N--2020-05-05--13.59.59--detections--6--car--38.8--101x35--169.203v270.238",
    "percentage_probability": 38.766613602638245,
    "box_points": [
      169,
      203,
      270,
      238
    ]
  },
  "733-681-N--2020-05-05--13.59.59--detections--7--car--84.9--122x72--235.166v357.238": {
    "type": "car",
    "id": "733-681-N--2020-05-05--13.59.59--detections--7--car--84.9--122x72--235.166v357.238",
    "percentage_probability": 84.940505027771,
    "box_points": [
      235,
      166,
      357,
      238
    ]
  }
}
