{
  "id": "733-681-N--2020-05-05--13.56.58--detections",
  "model": "ResNet50_COCO_best_v2.0.1.h5",
  "summary": {
    "total": 4,
    "car": 3,
    "motorcycle": 1
  },
  "733-681-N--2020-05-05--13.56.58--detections--1--car--39.4--8x8--108.49v116.57": {
    "type": "car",
    "id": "733-681-N--2020-05-05--13.56.58--detections--1--car--39.4--8x8--108.49v116.57",
    "percentage_probability": 39.38228487968445,
    "box_points": [
      108,
      49,
      116,
      57
    ]
  },
  "733-681-N--2020-05-05--13.56.58--detections--2--car--63.7--13x16--100.59v113.75": {
    "type": "car",
    "id": "733-681-N--2020-05-05--13.56.58--detections--2--car--63.7--13x16--100.59v113.75",
    "percentage_probability": 63.73753547668457,
    "box_points": [
      100,
      59,
      113,
      75
    ]
  },
  "733-681-N--2020-05-05--13.56.58--detections--3--motorcycle--33.2--19x46--78.133v97.179": {
    "type": "motorcycle",
    "id": "733-681-N--2020-05-05--13.56.58--detections--3--motorcycle--33.2--19x46--78.133v97.179",
    "percentage_probability": 33.194273710250854,
    "box_points": [
      78,
      133,
      97,
      179
    ]
  },
  "733-681-N--2020-05-05--13.56.58--detections--4--car--62.8--129x104--214.134v343.238": {
    "type": "car",
    "id": "733-681-N--2020-05-05--13.56.58--detections--4--car--62.8--129x104--214.134v343.238",
    "percentage_probability": 62.841713428497314,
    "box_points": [
      214,
      134,
      343,
      238
    ]
  }
}
