{
  "id": "733-681-N--2020-05-05--13.25.51--detections",
  "model": "ResNet50_COCO_best_v2.0.1.h5",
  "summary": {
    "total": 5,
    "car": 5
  },
  "733-681-N--2020-05-05--13.25.51--detections--1--car--48.9--8x9--117.52v125.61": {
    "type": "car",
    "id": "733-681-N--2020-05-05--13.25.51--detections--1--car--48.9--8x9--117.52v125.61",
    "percentage_probability": 48.862046003341675,
    "box_points": [
      117,
      52,
      125,
      61
    ]
  },
  "733-681-N--2020-05-05--13.25.51--detections--2--car--75.4--17x17--75.72v92.89": {
    "type": "car",
    "id": "733-681-N--2020-05-05--13.25.51--detections--2--car--75.4--17x17--75.72v92.89",
    "percentage_probability": 75.35196542739868,
    "box_points": [
      75,
      72,
      92,
      89
    ]
  },
  "733-681-N--2020-05-05--13.25.51--detections--3--car--32.7--15x9--100.74v115.83": {
    "type": "car",
    "id": "733-681-N--2020-05-05--13.25.51--detections--3--car--32.7--15x9--100.74v115.83",
    "percentage_probability": 32.7134370803833,
    "box_points": [
      100,
      74,
      115,
      83
    ]
  },
  "733-681-N--2020-05-05--13.25.51--detections--4--car--33.2--17x17--100.74v117.91": {
    "type": "car",
    "id": "733-681-N--2020-05-05--13.25.51--detections--4--car--33.2--17x17--100.74v117.91",
    "percentage_probability": 33.20123553276062,
    "box_points": [
      100,
      74,
      117,
      91
    ]
  },
  "733-681-N--2020-05-05--13.25.51--detections--5--car--81.6--20x15--99.80v119.95": {
    "type": "car",
    "id": "733-681-N--2020-05-05--13.25.51--detections--5--car--81.6--20x15--99.80v119.95",
    "percentage_probability": 81.62014484405518,
    "box_points": [
      99,
      80,
      119,
      95
    ]
  }
}
